SimpleRender
