Metadata-Version: 1.0
Name: SimpleRender
Version: 0.1.2
Summary: Takes a config file and a template and renders
Home-page: https://github.com/otternq/SimpleRender
Author: Nick Otter
Author-email: otternq@gmail.com
License: MIT
Platform: UNKNOWN
